cryptobob/__init__.py
cryptobob/cli.py
cryptobob/config.py
cryptobob/exceptions.py
cryptobob/kraken.py
cryptobob/runner.py
cryptobob/tradeplan.py
cryptobob/withdrawal.py
cryptobob-1.5.0.dist-info/licenses/LICENSE
cryptobob-1.5.0.dist-info/METADATA
cryptobob-1.5.0.dist-info/WHEEL
cryptobob-1.5.0.dist-info/entry_points.txt
cryptobob-1.5.0.dist-info/top_level.txt
cryptobob-1.5.0.dist-info/RECORD
