Metadata-Version: 2.4
Name: cryptobob
Version: 1.5.0
Summary: Automated trading bot for DCA crypto investments.
Author: confirm IT solutions
Project-URL: Homepage, https://confirm.ch/
Project-URL: Documentation, https://gitlab.confirm.ch/confirm/products/cryptobob/-/blob/main/README.md
Project-URL: Repository, https://gitlab.confirm.ch/confirm/products/cryptobob
Project-URL: Issues, https://gitlab.confirm.ch/confirm/products/cryptobob/-/issues
Project-URL: Changelog, https://gitlab.confirm.ch/confirm/products/cryptobob/-/releases
Classifier: Programming Language :: Python :: 3
Classifier: License :: OSI Approved :: MIT License
Classifier: Operating System :: OS Independent
Requires-Python: >=3.11
License-File: LICENSE
Requires-Dist: pyotp==2.9.0
Requires-Dist: PyYAML>=6.0.1
Provides-Extra: develop
Requires-Dist: build; extra == "develop"
Requires-Dist: confirm-tools; extra == "develop"
Requires-Dist: coverage; extra == "develop"
Requires-Dist: isort; extra == "develop"
Requires-Dist: pycodestyle; extra == "develop"
Requires-Dist: pylint; extra == "develop"
Dynamic: license-file
